promptsentry/__init__.py
promptsentry/__main__.py
promptsentry/cli.py
promptsentry/core/__init__.py
promptsentry/core/analyzer.py
promptsentry/core/detector.py
promptsentry/core/patterns.py
promptsentry/core/prompt_extractor.py
promptsentry/core/rules_loader.py
promptsentry/core/scoring.py
promptsentry/core/vectordb.py
promptsentry/git/__init__.py
promptsentry/git/hook.py
promptsentry/git/staged_files.py
promptsentry/llm/__init__.py
promptsentry/llm/base.py
promptsentry/llm/ollama.py
promptsentry/llm/ollama_manager.py
promptsentry/llm/prompts.py
promptsentry/llm/qwen.py
promptsentry/models/__init__.py
promptsentry/models/config.py
promptsentry/models/detection.py
promptsentry/models/issue.py
promptsentry/models/vulnerability.py
promptsentry/rules/owasp_llm_top10_guide.yaml
promptsentry/rules/patterns.yaml
promptsentry/tracker/__init__.py
promptsentry/tracker/database.py
promptsentry/tracker/differential.py
promptsentry/tracker/fingerprint.py
promptsentry/utils/__init__.py
promptsentry/utils/formatting.py
promptsentry/utils/hashing.py
promptsentry/utils/logger.py
promptsentry-0.2.0.dist-info/licenses/LICENSE
promptsentry-0.2.0.dist-info/METADATA
promptsentry-0.2.0.dist-info/WHEEL
promptsentry-0.2.0.dist-info/entry_points.txt
promptsentry-0.2.0.dist-info/top_level.txt
promptsentry-0.2.0.dist-info/RECORD
