Metadata-Version: 2.4
Name: promptsentry
Version: 0.2.0
Summary: AI prompt security scanner with differential validation - detects vulnerabilities before they reach production
Author: PromptSentry Team
License: MIT
Project-URL: Homepage, https://github.com/Brightlord5/PromptGuard
Project-URL: Repository, https://github.com/Brightlord5/PromptGuard
Project-URL: Issues, https://github.com/Brightlord5/PromptGuard/issues
Keywords: ai,llm,security,prompt-injection,pre-commit,owasp,vulnerability-scanner
Classifier: Development Status :: 3 - Alpha
Classifier: Intended Audience :: Developers
Classifier: License :: OSI Approved :: MIT License
Classifier: Programming Language :: Python :: 3.9
Classifier: Programming Language :: Python :: 3.10
Classifier: Programming Language :: Python :: 3.11
Classifier: Programming Language :: Python :: 3.12
Classifier: Topic :: Security
Classifier: Topic :: Software Development :: Quality Assurance
Requires-Python: >=3.9
License-File: LICENSE
Requires-Dist: click>=8.1.0
Requires-Dist: rich-click>=1.7.0
Requires-Dist: GitPython>=3.1.0
Requires-Dist: pydantic>=2.0.0
Requires-Dist: pyyaml>=6.0
Requires-Dist: rich>=13.0.0
Requires-Dist: ollama>=0.4.0
Provides-Extra: dev
Requires-Dist: pytest>=7.4.0; extra == "dev"
Requires-Dist: pytest-cov>=4.1.0; extra == "dev"
Requires-Dist: black>=23.0.0; extra == "dev"
Requires-Dist: ruff>=0.1.0; extra == "dev"
Requires-Dist: mypy>=1.5.0; extra == "dev"
Requires-Dist: pre-commit>=3.5.0; extra == "dev"
Dynamic: license-file
